bibliometa/__init__.py
bibliometa/config.py
bibliometa/configuration.py
bibliometa/conversion.py
bibliometa/graph/__init__.py
bibliometa/graph/analysis.py
bibliometa/graph/conversion.py
bibliometa/graph/similarity.py
bibliometa/graph/utils.py
bibliometa/utils/__init__.py
bibliometa/utils/archives.py
bibliometa/utils/utils.py
bibliometa-0.1.3.dist-info/LICENSE
bibliometa-0.1.3.dist-info/WHEEL
bibliometa-0.1.3.dist-info/METADATA
bibliometa-0.1.3.dist-info/RECORD
