Metadata-Version: 2.1
Name: bibliometa
Version: 0.1.3
Summary: A package for manipulating, converting and analysing bibliographic metadata
Home-page: https://bibliometa.readthedocs.io
License: MIT
Author: Andreas Lüschow
Author-email: lueschow@sub.uni-goettingen.de
Requires-Python: >=3.8,<3.10
Classifier: License :: OSI Approved :: MIT License
Classifier: Programming Language :: Python :: 3
Classifier: Programming Language :: Python :: 3.8
Requires-Dist: loguru (>=0.5.3,<0.6.0)
Requires-Dist: matplotlib (>=3.4.2,<4.0.0)
Requires-Dist: networkx (>=2.6.1,<3.0.0)
Requires-Dist: numpy (>=1.21.1,<2.0.0)
Requires-Dist: pandas (>=1.3.0,<2.0.0)
Requires-Dist: scipy (>=1.7.0,<2.0.0)
Requires-Dist: tqdm (>=4.61.2,<5.0.0)
Project-URL: Repository, https://github.com/alueschow/bibliometa
